{"imagePath":"cat-export_tex.png","width":512,"height":512,"name":"cat-export_ske","SubTexture":[{"x":261,"y":263,"width":100,"height":228,"name":"rightHand"},{"x":183,"y":136,"width":101,"height":82,"name":"rightLeg2"},{"x":183,"y":1,"width":130,"height":133,"name":"rightLeg"},{"x":1,"y":412,"width":148,"height":86,"name":"legs"},{"x":286,"y":136,"width":101,"height":82,"name":"leftLeg2"},{"x":363,"y":1,"width":130,"height":133,"name":"leftLeg"},{"x":1,"y":1,"width":180,"height":260,"name":"body"},{"x":159,"y":263,"width":100,"height":228,"name":"leftHand"},{"x":1,"y":263,"width":156,"height":147,"name":"head"}]}